pystructopt/VERSION.py
pystructopt/__init__.py
pystructopt/_dataclass_parser.py
pystructopt/_parse.py
pystructopt/_utils.py
pystructopt-0.1.7.dist-info/WHEEL
pystructopt-0.1.7.dist-info/METADATA
pystructopt-0.1.7.dist-info/RECORD
